mergedict.py
mergedict-1.0.0.dist-info/LICENSE
mergedict-1.0.0.dist-info/METADATA
mergedict-1.0.0.dist-info/WHEEL
mergedict-1.0.0.dist-info/top_level.txt
mergedict-1.0.0.dist-info/RECORD
