Metadata-Version: 2.1
Name: mergedict
Version: 1.0.0
Summary: A Python `dict` with a merge() method.
Home-page: https://github.com/schettino72/mergedict/
Author: Eduardo Naufel Schettino
Author-email: schettino72@gmail.com
License: MIT
Keywords: dict,singledispatch,config
Platform: any
Classifier: Development Status :: 4 - Beta
Classifier: Intended Audience :: Developers
Classifier: License :: OSI Approved :: MIT License
Classifier: Natural Language :: English
Classifier: Operating System :: OS Independent
Classifier: Programming Language :: Python
Classifier: Programming Language :: Python :: 3
Classifier: Programming Language :: Python :: 3.5
Classifier: Programming Language :: Python :: 3.6
Classifier: Programming Language :: Python :: 3.7
Classifier: Programming Language :: Python :: 3.8
Classifier: Programming Language :: Python :: 3 :: Only
Classifier: Topic :: Software Development :: Libraries
Classifier: Topic :: Software Development :: Libraries :: Python Modules
Requires-Python: >=3.4
